[
  {
    "id": "check_mental_vs_tn12",
    "name": "Mental Check vs TN 12",
    "desc": "Roll 1d20 + Mental modifier vs TN 12",
    "category": "check",
    "checkStat": "Mental",
    "checkVs": "fixed",
    "checkTN": 12
  },
  {
    "id": "check_mental_vs_tn10",
    "name": "Mental Check vs TN 10",
    "desc": "Roll 1d20 + Mental modifier vs TN 10",
    "category": "check",
    "checkStat": "Mental",
    "checkVs": "fixed",
    "checkTN": 10
  },
  {
    "id": "check_mental_vs_tn15",
    "name": "Mental Check vs TN 15",
    "desc": "Roll 1d20 + Mental modifier vs TN 15",
    "category": "check",
    "checkStat": "Mental",
    "checkVs": "fixed",
    "checkTN": 15
  },
  {
    "id": "check_physical_vs_tn10",
    "name": "Physical Check vs TN 10",
    "desc": "Roll 1d20 + Physical modifier vs TN 10",
    "category": "check",
    "checkStat": "Physical",
    "checkVs": "fixed",
    "checkTN": 10
  },
  {
    "id": "check_physical_vs_tn12",
    "name": "Physical Check vs TN 12",
    "desc": "Roll 1d20 + Physical modifier vs TN 12",
    "category": "check",
    "checkStat": "Physical",
    "checkVs": "fixed",
    "checkTN": 12
  },
  {
    "id": "check_physical_vs_tn15",
    "name": "Physical Check vs TN 15",
    "desc": "Roll 1d20 + Physical modifier vs TN 15",
    "category": "check",
    "checkStat": "Physical",
    "checkVs": "fixed",
    "checkTN": 15
  },
  {
    "id": "check_dexterity_vs_tn10",
    "name": "Dexterity Check vs TN 10",
    "desc": "Roll 1d20 + Dexterity modifier vs TN 10",
    "category": "check",
    "checkStat": "Dexterity",
    "checkVs": "fixed",
    "checkTN": 10
  },
  {
    "id": "check_dexterity_vs_tn12",
    "name": "Dexterity Check vs TN 12",
    "desc": "Roll 1d20 + Dexterity modifier vs TN 12",
    "category": "check",
    "checkStat": "Dexterity",
    "checkVs": "fixed",
    "checkTN": 12
  },
  {
    "id": "check_perception_vs_tn10",
    "name": "Perception Check vs TN 10",
    "desc": "Roll 1d20 + Perception modifier vs TN 10",
    "category": "check",
    "checkStat": "Perception",
    "checkVs": "fixed",
    "checkTN": 10
  },
  {
    "id": "check_perception_vs_tn12",
    "name": "Perception Check vs TN 12",
    "desc": "Roll 1d20 + Perception modifier vs TN 12",
    "category": "check",
    "checkStat": "Perception",
    "checkVs": "fixed",
    "checkTN": 12
  },
  {
    "id": "check_is_object_owner",
    "name": "Ownership Check",
    "desc": "Verify player is authorized owner",
    "category": "ownership",
    "requiresOwnership": true
  }
]
